pipe_save/__init__.py
pipe_save/save.py
pipe_save-0.1.0.dist-info/METADATA
pipe_save-0.1.0.dist-info/WHEEL
pipe_save-0.1.0.dist-info/top_level.txt
pipe_save-0.1.0.dist-info/RECORD
