Metadata-Version: 2.4
Name: pipe-save
Version: 0.1.0
Summary: pipe-save: a more structured version of tee
Requires-Python: >=3.12
Requires-Dist: python-dotenv>=1.2.1
